backports/pampy/__init__.py
backports/pampy/pampy.py
pampy/__init__.py
pampy/pampy.py
backports.pampy-0.1.10.dist-info/LICENSE
backports.pampy-0.1.10.dist-info/METADATA
backports.pampy-0.1.10.dist-info/WHEEL
backports.pampy-0.1.10.dist-info/top_level.txt
backports.pampy-0.1.10.dist-info/RECORD
