Metadata-Version: 2.1
Name: backports.pampy
Version: 0.1.10
Summary: The Pattern Matching for Python you always dreamed of
Home-page: https://github.com/santinic/pampy
Author: Claudio Santini
Author-email: hireclaudio@gmail.com
License: UNKNOWN
Platform: any
Classifier: Programming Language :: Python :: 2
Classifier: Programming Language :: Python :: 3
Classifier: License :: OSI Approved :: MIT License
Classifier: Operating System :: OS Independent
Requires-Dist: six
Requires-Dist: typing
